MANIFEST.in
setup.py
fastbloom/__init__.py
fastbloom/bitset.py
fastbloom/bloomfilter.py
fastbloom/hash_tools.py
fastbloom.egg-info/PKG-INFO
fastbloom.egg-info/SOURCES.txt
fastbloom.egg-info/dependency_links.txt
fastbloom.egg-info/requires.txt
fastbloom.egg-info/top_level.txt
fastbloom.egg-info/zip-safe
test/test_bloom_filter.py
test/test_mmap_bit_set.py