Metadata-Version: 1.1
Name: fastbloom
Version: 0.1.0
Summary: This is a lightweight but fast bloomfilter.
Home-page: https://github.com/preytaren/fastbloom
Author: preyta ren
Author-email: preyta@163.com
License: MIT
Keywords: bloomfilter,hash,bitset,python
Platform: UNKNOWN
Classifier: License :: OSI Approved :: MIT License
Classifier: Programming Language :: Python
Classifier: Programming Language :: Python :: 2.7
Classifier: Natural Language :: English
Classifier: Intended Audience :: Developers
Classifier: Operating System :: OS Independent
Classifier: Topic :: Software Development :: Libraries :: Python Modules
